censoredsummarystats/__init__.py
censoredsummarystats/censoredsummarystats.py
censoredsummarystats-1.0.1.dist-info/LICENSE
censoredsummarystats-1.0.1.dist-info/METADATA
censoredsummarystats-1.0.1.dist-info/WHEEL
censoredsummarystats-1.0.1.dist-info/RECORD
