Metadata-Version: 2.1
Name: censoredsummarystats
Version: 1.0.1
Summary: A python package for calculating summary stats on censored data (data that contains < and > symbols).
Home-page: https://github.com/kurtvanness/CensoredSummaryStats
Author: Kurt van Ness
Author-email: vanness.kurt@gmail.com
Requires-Python: >=3.9,<4.0
Classifier: Programming Language :: Python :: 3
Classifier: Programming Language :: Python :: 3.9
Classifier: Programming Language :: Python :: 3.10
Classifier: Programming Language :: Python :: 3.11
Requires-Dist: numpy (>=1.24.2,<2.0.0)
Project-URL: Repository, https://github.com/kurtvanness/CensoredSummaryStats
